himitsu/__init.py__
himitsu/client.py
himitsu/query.py
py_himitsu-0.0.10.dist-info/METADATA
py_himitsu-0.0.10.dist-info/WHEEL
py_himitsu-0.0.10.dist-info/licenses/COPYING
py_himitsu-0.0.10.dist-info/RECORD
