Metadata-Version: 2.4
Name: py-himitsu
Version: 0.0.10
Summary: Himitsu client pacakge
Project-URL: Homepage, https://git.sr.ht/~apreiml/py-himitsu
Author-email: Armin Preiml <apreiml@strohwolke.at>
License-Expression: MIT
License-File: COPYING
Classifier: Operating System :: POSIX
Classifier: Programming Language :: Python :: 3
Requires-Python: >=3.8
Requires-Dist: pyxdg~=0.28
